{
  "event": {
    "number": 286,
    "dateIso": "2023-06-18",
    "city": "г. Таганрог",
    "park": "ПКиО им. Горького",
    "clubName": "КЛБ «Легенда»",
    "chairman": "В.С. Хахуцкий"
  },
  "rows": [
    {
      "index": 1,
      "fullName": "Троилин Антон",
      "time23": "08:54",
      "time5": "19:34",
      "totalMs": 1174000,
      "distanceKm": 5,
      "gender": "M",
      "placeM": 1,
      "placeF": null,
      "club": "",
      "note": ""
    },
    {
      "index": 2,
      "fullName": "Ширшов Денис",
      "time23": "09:31",
      "time5": "20:53",
      "totalMs": 1253000,
      "distanceKm": 5,
      "gender": "M",
      "placeM": 2,
      "placeF": null,
      "club": "",
      "note": ""
    },
    {
      "index": 3,
      "fullName": "Дорожкин Михаил",
      "time23": "09:42",
      "time5": "21:33",
      "totalMs": 1293000,
      "distanceKm": 5,
      "gender": "M",
      "placeM": 3,
      "placeF": null,
      "club": "",
      "note": ""
    },
    {
      "index": 4,
      "fullName": "Скляр Артем",
      "time23": "10:20",
      "time5": "23:16",
      "totalMs": 1396000,
      "distanceKm": 5,
      "gender": "M",
      "placeM": 4,
      "placeF": null,
      "club": "",
      "note": ""
    },
    {
      "index": 5,
      "fullName": "Беликов Дмитрий",
      "time23": "11:24",
      "time5": "25:47",
      "totalMs": 1547000,
      "distanceKm": 5,
      "gender": "M",
      "placeM": 5,
      "placeF": null,
      "club": "",
      "note": ""
    },
    {
      "index": 6,
      "fullName": "Климачкин Валерий",
      "time23": "11:24",
      "time5": "25:49",
      "totalMs": 1549000,
      "distanceKm": 5,
      "gender": "M",
      "placeM": 6,
      "placeF": null,
      "club": "",
      "note": "Первое участие"
    },
    {
      "index": 7,
      "fullName": "Шкарупа Владислав",
      "time23": "11:31",
      "time5": "DNF",
      "totalMs": null,
      "distanceKm": null,
      "gender": "M",
      "placeM": null,
      "placeF": null,
      "club": "",
      "note": "DNF"
    }
  ],
  "schemaVersion": 1
}
